feishu_notify_mcp/server.py
feishu_notify_mcp-0.0.1.dist-info/METADATA
feishu_notify_mcp-0.0.1.dist-info/WHEEL
feishu_notify_mcp-0.0.1.dist-info/entry_points.txt
feishu_notify_mcp-0.0.1.dist-info/top_level.txt
feishu_notify_mcp-0.0.1.dist-info/RECORD
