Metadata-Version: 2.4
Name: feishu-notify-mcp
Version: 0.0.1
Summary: Feishu Notify MCP Server
Author-email: FeishuNotify <support@example.com>
Keywords: mcp,lark
Requires-Python: >=3.11
Requires-Dist: build>=1.2.2.post1
Requires-Dist: lark>=1.2.2
Requires-Dist: lark-oapi>=1.4.15
Requires-Dist: mcp[cli]>=1.6.0
Requires-Dist: requests>=2.32.3
Requires-Dist: setuptools>=45
Requires-Dist: twine>=6.1.0
